explorium_mcp_server/__init__.py
explorium_mcp_server/__main__.py
explorium_mcp_server/models/__init__.py
explorium_mcp_server/models/businesses.py
explorium_mcp_server/models/enum_types.py
explorium_mcp_server/models/prospects.py
explorium_mcp_server/models/shared.py
explorium_mcp_server/tools/__init__.py
explorium_mcp_server/tools/businesses.py
explorium_mcp_server/tools/prospects.py
explorium_mcp_server/tools/shared.py
explorium_mcp_server-0.2.11.dist-info/METADATA
explorium_mcp_server-0.2.11.dist-info/WHEEL
explorium_mcp_server-0.2.11.dist-info/entry_points.txt
explorium_mcp_server-0.2.11.dist-info/licenses/LICENSE.md
explorium_mcp_server-0.2.11.dist-info/RECORD
