Metadata-Version: 2.4
Name: explorium-mcp-server
Version: 0.2.11
Summary: MCP server for interacting with the Explorium API.
License-File: LICENSE.md
Requires-Python: >=3.10
Requires-Dist: backoff>=2.2.1
Requires-Dist: dotenv>=0.9.9
Requires-Dist: fastmcp>=2.3.3
Requires-Dist: mcp[cli]>=1.3.0
Requires-Dist: requests>=2.32.3
